{
"companyName": "DefaultCompany",
"productName": "Endless Runner",
"dataUrl": "Endless Runner Web Build 1.data.unityweb",
"asmCodeUrl": "Endless Runner Web Build 1.asm.code.unityweb",
"asmMemoryUrl": "Endless Runner Web Build 1.asm.memory.unityweb",
"asmFrameworkUrl": "Endless Runner Web Build 1.asm.framework.unityweb",
"TOTAL_MEMORY": 268435456,
"graphicsAPI": ["WebGL 2.0", "WebGL 1.0"],
"webglContextAttributes": {"preserveDrawingBuffer": false},
"splashScreenStyle": "Dark",
"backgroundColor": "#231F20"
}